loger/__init__.py
loger/config_client_log.py
src/__init__.py
src/client.py
src/client_ui.py
src/launcher.py
src/metaclasses.py
src/utils_client.py
src/variables_client.py
shark_cli-1.0.1.dist-info/METADATA
shark_cli-1.0.1.dist-info/WHEEL
shark_cli-1.0.1.dist-info/top_level.txt
shark_cli-1.0.1.dist-info/RECORD
