Metadata-Version: 2.1
Name: shark-cli
Version: 1.0.1
Summary: shark_cli
Author: taygish
Author-email: spacedicknew@gmail.com
Requires-Dist: PyQt5
Requires-Dist: sqlalchemy
Requires-Dist: pycryptodome
Requires-Dist: pycryptodomex
